{
  "name": "Rebecca Spencer",
  "age": 39,
  "address": {
    "street": "Tanmof Heights",
    "city": "Fenita",
    "state": "NC",
    "zip": "68896"
  },
  "contact": {
    "phone": "(258) 817-3596",
    "servicePhone": "800856217"
  },
  "birthday": "1992-02-07T03:01:17.621Z",
  "ip": "145.28.11.65",
  "foo": "bar",
  "profile": {
    "about": "Ekjub zortogek ow ebbos duftajo duv is rutviti funar huriepa lihit zute gasumaf lecojwa. Fim peko poneb eg huzil fogkapjet gev secime nucaseku wasbapiba vu gug unibar vu rid. Him ok izteji fut rodzuf aj ugtamjaf tigudop uwuko ir ri odaliajo cujhibut.",
    "bio": "Le pib ef ozbec vuhjubbo vekokgu hucsage evo saptob suf fih ubehe zooteru duzasu ilwev. Eka ta zitvosow mez sujwa uhjonid burebe simdetkek rukutef wid kuc isaaf bomvaum nagge jestozo kotfe. It guftade vumsecmo paghisju nurmibmob tous zo gejko fohcom taku votu nagiphaf ga ni ukfieme tuv esagazo. Bekadopo tunalsur arkuw wigditkih beeraw curobu tas pi esi ef jof geneno febaiku vic wihjo rupef sevekjoj. Fimu maebuwak ic jusvu ba ibesiig wirmo tesib jiizika vafecjo wuhu dozonojew."
  },
  "apiKey": "9b62d0dd95fff8a6b29c126820e338ca3da25192c6ea03d268ff6c8eed3f6796",
  "currency": {
    "code": "BYR",
    "name": "Belarus Ruble"
  }
}