{
  "name": "Amy Barber",
  "age": 55,
  "address": {
    "street": "Siub Loop",
    "city": "Pokpuse",
    "state": "WV",
    "zip": "64432"
  },
  "contact": {
    "phone": "(244) 622-7731",
    "servicePhone": "800763265"
  },
  "birthday": "1983-11-15T23:54:45.272Z",
  "ip": "127.102.147.226",
  "foo": "bar",
  "profile": {
    "about": "Ilobu ci ida wowilude aljeme kabfumbeg re afuejotos iwova vub ce iwikutsik nujof his sik. Mewbebma cegijo zipjuket hepecoguj set cuumawam pelej ri gomijlu ejacahmoj ko caotehur. Giipe zekopo paligu put zah muszu tucetu defirhem uvwokzod ejtudun hu irgaid cip hihdab uwtan as.",
    "bio": "Hadno licpativ dolsig conku liki vi gi zusim wankugego turokse udhuk go cu juhriguc tic hah eba. Bib nusanzij zajekkuj soccuc gaebcu gezdeso mu bug nikcatcu misupi ideceino hiv. Pelfop jowfe zusos hil locepob ma imule eh wujgutul ov amutascok zofdagace. Tor kiucde deejo dukwad mubek wuiwfoz bup veivaepa inlinjag suijjo ikadawva ihadi lir pos."
  },
  "apiKey": "cab8fd3c29a7993d829aaca8839aefb549ea9fa18551c6a1dff949de5b2e5861",
  "currency": {
    "code": "SCR",
    "name": "Seychelles Rupee"
  }
}